MANIFEST.in
setup.py
exifrenamer/__init__.py
exifrenamer/exifrenamer.py
exifrenamer.egg-info/PKG-INFO
exifrenamer.egg-info/SOURCES.txt
exifrenamer.egg-info/dependency_links.txt
exifrenamer.egg-info/requires.txt
exifrenamer.egg-info/top_level.txt