Metadata-Version: 1.1
Name: exifrenamer
Version: 0.3.1
Summary: Organize photos based on timestamp metadata.
Home-page: https://github.com/wting/exifrenamer
Author: William Ting
Author-email: io@williamting.com
License: GPL v3
Platform: UNKNOWN
Classifier: Development Status :: 4 - Beta
Classifier: Environment :: Console
Classifier: Intended Audience :: Developers
Classifier: License :: OSI Approved :: GNU General Public License v3 or later (GPLv3+)
Classifier: Programming Language :: Python
Classifier: Programming Language :: Python :: 2.7
Classifier: Topic :: Multimedia :: Graphics :: Graphics Conversion
